dgen_py/__init__.py
dgen_py/__init__.pyi
dgen_py/_dgen_rs.cpython-312-x86_64-linux-gnu.so
dgen_py/docs/PERFORMANCE.md
dgen_py/examples/README.md
dgen_py/examples/benchmark_cpu_numa.py
dgen_py/examples/benchmark_vs_numpy.py
dgen_py/examples/demo.py
dgen_py/examples/quick_perf_test.py
dgen_py/examples/zero_copy_demo.py
dgen_py-0.1.7.dist-info/METADATA
dgen_py-0.1.7.dist-info/WHEEL
dgen_py-0.1.7.dist-info/licenses/LICENSE
dgen_py.libs/libhwloc-a765a097.so.15
dgen_py-0.1.7.dist-info/RECORD
