Metadata-Version: 2.4
Name: dgen-py
Version: 0.1.7
Classifier: Development Status :: 4 - Beta
Classifier: Intended Audience :: Developers
Classifier: License :: OSI Approved :: MIT License
Classifier: License :: OSI Approved :: Apache Software License
Classifier: Programming Language :: Python :: 3.10
Classifier: Programming Language :: Python :: 3.11
Classifier: Programming Language :: Python :: 3.12
Classifier: Programming Language :: Rust
Classifier: Topic :: Software Development :: Libraries
Classifier: Topic :: System :: Benchmark
Requires-Dist: numpy>=1.21.0
Requires-Dist: zstandard>=0.25.0
Requires-Dist: pytest>=8.0.0 ; extra == 'dev'
Requires-Dist: pytest-benchmark>=4.0.0 ; extra == 'dev'
Requires-Dist: maturin>=1.0.0 ; extra == 'dev'
Requires-Dist: numpy>=2.0.0 ; extra == 'numpy'
Provides-Extra: dev
Provides-Extra: numpy
License-File: LICENSE
Summary: High-performance random data generation with NUMA optimization and zero-copy Python interface
Keywords: data-generation,benchmark,numa,performance,zero-copy
Author-email: Russ Fellows <russ.fellows@gmail.com>
License: MIT OR Apache-2.0
Requires-Python: >=3.10
